Gsub/GUI_build_linux.spec
Gsub/GUI_build_windows.spec
Gsub/VERSION
Gsub/__init.py__
Gsub/_version.py
Gsub/submission_GenBank_UI.py
Gsub/image/GUI_exemple.png
Gsub/image/program_icon.ico
Gsub/image/program_icon.png
Gsub/tools/Polymerase.hmm
Gsub/tools/table2asn.linux
Gsub/tools/tbl2asn.linux
Gsub/tools/table2asn.windows/ncbi-vdb-md.dll
Gsub/tools/table2asn.windows/nghttp2.dll
Gsub/tools/table2asn.windows/table2asn.exe
Gsub/tools/tbl2asn.windows/libgcc_s_seh-1.dll
Gsub/tools/tbl2asn.windows/libgmp-10.dll
Gsub/tools/tbl2asn.windows/libgnutls-30.dll
Gsub/tools/tbl2asn.windows/libhogweed-4-2.dll
Gsub/tools/tbl2asn.windows/libnettle-6-2.dll
Gsub/tools/tbl2asn.windows/libp11-kit-0.dll
Gsub/tools/tbl2asn.windows/tbl2asn.exe
Gsub/tools/tbl2asn.windows/vcruntime140.dll
Gsub/tools/tbl2asn.windows/vcruntime140_1.dll
Gsub_tools-2.0.0.dist-info/LICENSE
Gsub_tools-2.0.0.dist-info/METADATA
Gsub_tools-2.0.0.dist-info/WHEEL
Gsub_tools-2.0.0.dist-info/entry_points.txt
Gsub_tools-2.0.0.dist-info/top_level.txt
Gsub_tools-2.0.0.dist-info/RECORD
